mssqlclient_ng/__init__.py
mssqlclient_ng/__main__.py
mssqlclient_ng/banner.py
mssqlclient_ng/cli.py
mssqlclient_ng/core/actions/__init__.py
mssqlclient_ng/core/actions/administration/__init__.py
mssqlclient_ng/core/actions/administration/config.py
mssqlclient_ng/core/actions/administration/createuser.py
mssqlclient_ng/core/actions/administration/kill.py
mssqlclient_ng/core/actions/administration/monitor.py
mssqlclient_ng/core/actions/administration/sessions.py
mssqlclient_ng/core/actions/administration/trustworthy.py
mssqlclient_ng/core/actions/base.py
mssqlclient_ng/core/actions/database/__init__.py
mssqlclient_ng/core/actions/database/authtoken.py
mssqlclient_ng/core/actions/database/databases.py
mssqlclient_ng/core/actions/database/impersonate.py
mssqlclient_ng/core/actions/database/info.py
mssqlclient_ng/core/actions/database/loginmap.py
mssqlclient_ng/core/actions/database/oledb_providers.py
mssqlclient_ng/core/actions/database/permissions.py
mssqlclient_ng/core/actions/database/procedures.py
mssqlclient_ng/core/actions/database/rolemembers.py
mssqlclient_ng/core/actions/database/roles.py
mssqlclient_ng/core/actions/database/rows.py
mssqlclient_ng/core/actions/database/search.py
mssqlclient_ng/core/actions/database/tables.py
mssqlclient_ng/core/actions/database/users.py
mssqlclient_ng/core/actions/database/whoami.py
mssqlclient_ng/core/actions/database/xprocs.py
mssqlclient_ng/core/actions/domain/__init__.py
mssqlclient_ng/core/actions/domain/addomain.py
mssqlclient_ng/core/actions/domain/adgroups.py
mssqlclient_ng/core/actions/domain/admembers.py
mssqlclient_ng/core/actions/domain/adsid.py
mssqlclient_ng/core/actions/domain/ridcycle.py
mssqlclient_ng/core/actions/execution/__init__.py
mssqlclient_ng/core/actions/execution/agents.py
mssqlclient_ng/core/actions/execution/clr.py
mssqlclient_ng/core/actions/execution/exec_file.py
mssqlclient_ng/core/actions/execution/ole.py
mssqlclient_ng/core/actions/execution/powershell.py
mssqlclient_ng-0.9.0.dist-info/WHEEL
mssqlclient_ng-0.9.0.dist-info/entry_points.txt
mssqlclient_ng-0.9.0.dist-info/METADATA
mssqlclient_ng-0.9.0.dist-info/RECORD
