Metadata-Version: 2.3
Name: mssqlclient-ng
Version: 0.9.0
Summary: Enhanced version of impacket's mssqlclient.py. It lets you interact with Microsoft SQL Server (MS SQL / MSSQL) servers and their linked instances, impersonating any account encountered along the way, without requiring complex T-SQL queries.
Author: n3rada
Author-email: n3rada <72791564+n3rada@users.noreply.github.com>
License: GPL-3.0-or-later
Requires-Dist: loguru>=0.7.3,<0.8.0
Requires-Dist: prompt-toolkit>=3.0.52,<4.0.0
Requires-Dist: pygments>=2.19.2,<3.0.0
Requires-Dist: impacket>=0.13.0,<0.14.0
Requires-Python: >=3.9, <4.0
Project-URL: documentation, https://github.com/n3rada/mssqlclient-ng/blob/main/README.md
Project-URL: homepage, https://github.com/n3rada/mssqlclient-ng
Project-URL: repository, https://github.com/n3rada/mssqlclient-ng
